_abovo.cpython-312-darwin.so
abovo/__init__.py
abovo-0.1.4.dist-info/licenses/LICENSE
abovo-0.1.4.dist-info/METADATA
abovo-0.1.4.dist-info/WHEEL
abovo-0.1.4.dist-info/top_level.txt
abovo-0.1.4.dist-info/RECORD
