Metadata-Version: 2.4
Name: abovo
Version: 0.1.4
Summary: A C++ neural network engine with Python bindings, designed for educational performance optimization.
Classifier: Programming Language :: Python :: 3
Classifier: Programming Language :: C++
Classifier: Operating System :: MacOS
Classifier: Operating System :: POSIX :: Linux
Classifier: Operating System :: Microsoft :: Windows
Classifier: License :: OSI Approved :: MIT License
Classifier: Development Status :: 3 - Alpha
Classifier: Topic :: Scientific/Engineering :: Artificial Intelligence
Requires-Python: >=3.7
License-File: LICENSE
Provides-Extra: docs
Requires-Dist: sphinx>=4.0.0; extra == "docs"
Requires-Dist: sphinx-rtd-theme; extra == "docs"
Requires-Dist: sphinx_autodoc_typehints; extra == "docs"
Dynamic: classifier
Dynamic: description
Dynamic: description-content-type
Dynamic: license-file
Dynamic: provides-extra
Dynamic: requires-python
Dynamic: summary
